buridan_ui/__init__.py
buridan_ui/blueprints/__init__.py
buridan_ui/blueprints/anon/__init__.py
buridan_ui/blueprints/anon/components/__init__.py
buridan_ui/blueprints/anon/components/borders.py
buridan_ui/blueprints/anon/main.py
buridan_ui/blueprints/anon/state.py
buridan_ui/blueprints/anon/style.py
buridan_ui/blueprints/dashboards/__init__.py
buridan_ui/blueprints/dashboards/dashboard_app/__init__.py
buridan_ui/blueprints/dashboards/dashboard_app/main.py
buridan_ui/blueprints/dashboards/dashboard_app/state.py
buridan_ui/blueprints/dashboards/dashboard_app/style.py
buridan_ui/blueprints/dashboards/dashboard_components/__init__.py
buridan_ui/blueprints/dashboards/dashboard_components/employeeTable/__init__.py
buridan_ui/blueprints/dashboards/dashboard_components/employeeTable/main.py
buridan_ui/blueprints/dashboards/dashboard_components/expenseBar/__init__.py
buridan_ui/blueprints/dashboards/dashboard_components/expenseBar/main.py
buridan_ui/blueprints/dashboards/dashboard_components/expenseBar/style.py
buridan_ui/blueprints/dashboards/dashboard_components/navBar/__init__.py
buridan_ui/blueprints/dashboards/dashboard_components/navBar/main.py
buridan_ui/blueprints/dashboards/dashboard_components/navBar/style.py
buridan_ui/blueprints/dashboards/dashboard_components/sideBar/__init__.py
buridan_ui/blueprints/dashboards/dashboard_components/sideBar/main.py
buridan_ui/blueprints/dashboards/dashboard_components/sideBar/style.py
buridan_ui/blueprints/dashboards/dashboard_components/statBar/__init__.py
buridan_ui/blueprints/dashboards/dashboard_components/statBar/main.py
buridan_ui/blueprints/dashboards/dashboard_components/statBar/style.py
buridan_ui/blueprints/dashboards/dashboard_components/trafficBar/__init__.py
buridan_ui/blueprints/dashboards/dashboard_components/trafficBar/main.py
buridan_ui/blueprints/dashboards/dashboard_components/trafficBar/style.py
buridan_ui/blueprints/exports.py
buridan_ui/blueprints/layouts/__init__.py
reflex_ai-0.1.0a39.dist-info/METADATA
reflex_ai-0.1.0a39.dist-info/WHEEL
reflex_ai-0.1.0a39.dist-info/RECORD
